Metadata-Version: 1.1
Name: prueba-ifsER
Version: 0.1.0
Summary: paquete de prueba prueba_ifsER
Home-page: https://github.com/NildaX/python-prueba_ifsER
Author: Nilda G.Xolo  Tlapanco
Author-email: nilda_gaby_9745@live.com.mx
License: MIT
Keywords: testing,IFS,example
Platform: UNKNOWN
Classifier: Programming Language :: Python :: 3.4
